LICENSE
MANIFEST.in
README.txt
sapling.py
setup.py
saplib/__init__.py
saplib/config.py
saplib/lib.py
saplib/split.py
sapling.egg-info/PKG-INFO
sapling.egg-info/SOURCES.txt
sapling.egg-info/dependency_links.txt
sapling.egg-info/requires.txt
sapling.egg-info/top_level.txt
sapversion/__init__.py
sapversion/version.txt
test/test-config.py
test/test-lib.py
test/test-split.py