Metadata-Version: 1.1
Name: sapling
Version: 0.0.11
Summary: A git porcelain to manage bidirectional subtree syncing with foreign git repositories
Home-page: http://github.com/jsirois/sapling
Author: John Sirois
Author-email: john.sirois@gmail.com
License: Apache License Version 2.0
Platform: UNKNOWN
Classifier: Programming Language :: Python
Classifier: Programming Language :: Python :: 2.6
Classifier: Development Status :: 2 - Pre-Alpha
Classifier: Environment :: Console
Classifier: Intended Audience :: Developers
Classifier: License :: OSI Approved :: Apache Software License
Classifier: Operating System :: OS Independent
Classifier: Topic :: Software Development :: Version Control
Provides: s
Provides: a
Provides: p
Provides: l
Provides: i
Provides: n
Provides: g
